iis_frida/__init__.py
iis_frida/model/__init__.py
iis_frida/model/common/__init__.py
iis_frida/model/common/calculator.py
iis_frida/utils/__init__.py
iis_frida-1.2.dist-info/METADATA
iis_frida-1.2.dist-info/WHEEL
iis_frida-1.2.dist-info/top_level.txt
iis_frida-1.2.dist-info/RECORD
